google_assistant_grpc-0.3.0-py3.5-nspkg.pth
google/assistant/embedded/v1alpha1/__init__.py
google/assistant/embedded/v1alpha1/embedded_assistant_pb2.py
google/assistant/embedded/v1alpha1/embedded_assistant_pb2_grpc.py
google/assistant/embedded/v1alpha2/__init__.py
google/assistant/embedded/v1alpha2/embedded_assistant_pb2.py
google/assistant/embedded/v1alpha2/embedded_assistant_pb2_grpc.py
google_assistant_grpc-0.3.0.dist-info/LICENSE
google_assistant_grpc-0.3.0.dist-info/METADATA
google_assistant_grpc-0.3.0.dist-info/WHEEL
google_assistant_grpc-0.3.0.dist-info/namespace_packages.txt
google_assistant_grpc-0.3.0.dist-info/top_level.txt
google_assistant_grpc-0.3.0.dist-info/RECORD
