Metadata-Version: 2.1
Name: google-assistant-grpc
Version: 0.3.0
Summary: Google Assistant API gRPC bindings
Home-page: https://github.com/googlesamples/assistant-sdk-python
Author: Google Assistant SDK team
Author-email: proppy+assistant-sdk@google.com
License: Apache 2.0
Keywords: google assistant api grpc
Platform: UNKNOWN
Classifier: Programming Language :: Python :: 2
Classifier: Programming Language :: Python :: 2.7
Classifier: Programming Language :: Python :: 3
Classifier: Programming Language :: Python :: 3.4
Classifier: Programming Language :: Python :: 3.5
Classifier: Development Status :: 4 - Beta
Classifier: Intended Audience :: Developers
Classifier: License :: OSI Approved :: Apache Software License
Classifier: Operating System :: POSIX
Classifier: Operating System :: Microsoft :: Windows
Classifier: Operating System :: MacOS :: MacOS X
Classifier: Operating System :: OS Independent
Classifier: Topic :: Internet :: WWW/HTTP
Requires-Dist: googleapis-common-protos (>=1.5.2)
Requires-Dist: grpcio (>=1.3.5)
